MANIFEST.in
gh-pages
license.txt
makefile
readme.rst
requirements.txt
setup.py
urlmark.py
UrlMark.egg-info/PKG-INFO
UrlMark.egg-info/SOURCES.txt
UrlMark.egg-info/dependency_links.txt
UrlMark.egg-info/entry_points.txt
UrlMark.egg-info/requires.txt
UrlMark.egg-info/top_level.txt
gh-pages/left.md
gh-pages/right.md
gh-pages/template.html
urlmark/__init__.py
urlmark/__main__.py
urlmark/main.py