Metadata-Version: 1.1
Name: UrlMark
Version: 0.4.0
Summary: UrlMark
Home-page: https://github.com/NoviceLive/urlmark
Author: Gu Zhengxiong
Author-email: rectigu@gmail.com
License: GPL-3
Keywords: Home page,Bookmarks,URLs,Favorite sites
Platform: UNKNOWN
Classifier: Development Status :: 4 - Beta
Classifier: Environment :: Console
Classifier: License :: OSI Approved :: GNU General Public License v3 or later (GPLv3+)
Classifier: Operating System :: OS Independent
Classifier: Programming Language :: Python :: 2.7
Classifier: Programming Language :: Python :: 3
